Metadata-Version: 2.4
Name: topsis-harshita-102353012
Version: 1.0.1
Summary: A Python package for TOPSIS decision making
Author: Harshita Goyal
Author-email: harshitagoyal1405@gmail.com
Requires-Python: >=3.7
Requires-Dist: pandas
Requires-Dist: numpy
Dynamic: author
Dynamic: author-email
Dynamic: description
Dynamic: description-content-type
Dynamic: requires-dist
Dynamic: requires-python
Dynamic: summary
